[
  {
    "py/object": "model.group.Group",
    "footer": "",
    "header": "",
    "id": null,
    "name": ""
  },
  {
    "py/object": "model.group.Group",
    "footer": "footer",
    "header": "headerZY4cXz",
    "id": null,
    "name": "name2Bu A"
  },
  {
    "py/object": "model.group.Group",
    "footer": "footer4PhSGW",
    "header": "headerDRml Chp7K",
    "id": null,
    "name": "namePe6y vs"
  },
  {
    "py/object": "model.group.Group",
    "footer": "footerAWd6 A c",
    "header": "header",
    "id": null,
    "name": "nameK6Vb"
  },
  {
    "py/object": "model.group.Group",
    "footer": "footer0Wk6 XaJ5uRPNbJ",
    "header": "headern8g",
    "id": null,
    "name": "namenKv G "
  },
  {
    "py/object": "model.group.Group",
    "footer": "footer1CK",
    "header": "header6Ks",
    "id": null,
    "name": "name"
  },
  {
    "py/object": "model.group.Group",
    "footer": "footeryphWYPDLzRFR44Gk4q",
    "header": "header B 5b ",
    "id": null,
    "name": "name"
  },
  {
    "py/object": "model.group.Group",
    "footer": "footerxH9ETZQ1  JlbNw7",
    "header": "header UWgth4zI",
    "id": null,
    "name": "name 2acP eT"
  },
  {
    "py/object": "model.group.Group",
    "footer": "footer5UM5 mmR IagK8",
    "header": "headerI8 e2 xXbzb",
    "id": null,
    "name": "nameubAG  0 "
  },
  {
    "py/object": "model.group.Group",
    "footer": "footerMXy ZnFZrAvWsbTudm",
    "header": "header G",
    "id": null,
    "name": "name8gizy X"
  },
  {
    "py/object": "model.group.Group",
    "footer": "footermEYkFliwOU",
    "header": "header k1ljm d0JAOGA",
    "id": null,
    "name": "name nuy"
  }
]